pymahjongutil/__init__.py
pymahjongutil/enum/__init__.py
pymahjongutil/enum/common.py
pymahjongutil/hand_checker/__init__.py
pymahjongutil/hand_checker/hand_checker.py
pymahjongutil/hand_checker/normal_checker.py
pymahjongutil/hand_checker/riichi_checker.py
pymahjongutil/hand_checker/seven_pair_checker.py
pymahjongutil/hand_checker/thirteen_orphan_checker.py
pymahjongutil/hand_parser.py
pymahjongutil/point_calculator/__init__.py
pymahjongutil/point_calculator/fu_calculator.py
pymahjongutil/point_calculator/han_calculator.py
pymahjongutil/point_calculator/point_calculator.py
pymahjongutil/rule/__init__.py
pymahjongutil/rule/riichi_default_rule.py
pymahjongutil/schema/__init__.py
pymahjongutil/schema/agari_info.py
pymahjongutil/schema/call.py
pymahjongutil/schema/count.py
pymahjongutil/schema/division.py
pymahjongutil/schema/efficiency_data.py
pymahjongutil/schema/hand.py
pymahjongutil/schema/point_info.py
pymahjongutil/schema/tile.py
pymahjongutil/schema/yaku_rule.py
pymahjongutil/yaku_checker/__init__.py
pymahjongutil/yaku_checker/all_greens.py
pymahjongutil/yaku_checker/all_honors.py
pymahjongutil/yaku_checker/all_sequences.py
pymahjongutil/yaku_checker/all_simples.py
pymahjongutil/yaku_checker/all_terminals.py
pymahjongutil/yaku_checker/all_terminals_and_honors.py
pymahjongutil/yaku_checker/all_triplets.py
pymahjongutil/yaku_checker/base_yaku.py
pymahjongutil/yaku_checker/big_four_winds.py
pymahjongutil/yaku_checker/big_three_dragons.py
pymahjongutil/yaku_checker/dead_wall_draw.py
pymahjongutil/yaku_checker/double_ready.py
pymahjongutil/yaku_checker/earthly_hand.py
pymahjongutil/yaku_checker/flush.py
pymahjongutil/yaku_checker/four_concealed_triplets.py
pymahjongutil/yaku_checker/four_quads.py
pymahjongutil/yaku_checker/green_dragon.py
pymahjongutil/yaku_checker/half_flush.py
pymahjongutil/yaku_checker/half_outside_hand.py
pymahjongutil/yaku_checker/heavenly_hand.py
pymahjongutil/yaku_checker/identical_sequences.py
pymahjongutil/yaku_checker/nine_gates.py
pymahjongutil-0.1.0.dist-info/METADATA
pymahjongutil-0.1.0.dist-info/WHEEL
pymahjongutil-0.1.0.dist-info/RECORD
