Metadata-Version: 2.1
Name: pymahjongutil
Version: 0.1.0
Summary: 
Author: Taeho Gwon
Author-email: taehogwon96@gmail.com
Requires-Python: >=3.11,<4.0
Classifier: Programming Language :: Python :: 3
Classifier: Programming Language :: Python :: 3.11
Requires-Dist: numpy (>=1.24.3,<2.0.0)
Requires-Dist: pydantic (>=1.9.0,<2.0.0)
